odoo8_addon_web_no_crawler-8.0.1.0.0.99.dev3-nspkg.pth
odoo_addons/web_no_crawler/README.rst
odoo_addons/web_no_crawler/__init__.py
odoo_addons/web_no_crawler/__openerp__.py
odoo_addons/web_no_crawler/controllers/__init__.py
odoo_addons/web_no_crawler/controllers/main.py
odoo_addons/web_no_crawler/i18n/web_no_crawler.pot
odoo_addons/web_no_crawler/readme/CONTRIBUTORS.rst
odoo_addons/web_no_crawler/readme/CREDITS.rst
odoo_addons/web_no_crawler/readme/DESCRIPTION.rst
odoo_addons/web_no_crawler/readme/INSTALL.rst
odoo_addons/web_no_crawler/readme/ROADMAP.rst
odoo_addons/web_no_crawler/readme/USAGE.rst
odoo_addons/web_no_crawler/static/description/icon.png
odoo_addons/web_no_crawler/static/description/index.html
odoo8_addon_web_no_crawler-8.0.1.0.0.99.dev3.dist-info/METADATA
odoo8_addon_web_no_crawler-8.0.1.0.0.99.dev3.dist-info/WHEEL
odoo8_addon_web_no_crawler-8.0.1.0.0.99.dev3.dist-info/namespace_packages.txt
odoo8_addon_web_no_crawler-8.0.1.0.0.99.dev3.dist-info/top_level.txt
odoo8_addon_web_no_crawler-8.0.1.0.0.99.dev3.dist-info/RECORD
